staygreen/__init__.py
staygreen/__main__.py
staygreen/green.py
staygreen-0.3.2.dist-info/METADATA
staygreen-0.3.2.dist-info/WHEEL
staygreen-0.3.2.dist-info/entry_points.txt
staygreen-0.3.2.dist-info/RECORD
